evalyn_sdk_harishatmecs/sdk/__init__.py
evalyn_sdk_harishatmecs/sdk/constants.py
evalyn_sdk_harishatmecs/sdk/evaluator.py
evalyn_sdk_harishatmecs/sdk/exceptions.py
evalyn_sdk_harishatmecs/sdk/utils.py
evalyn_sdk_harishatmecs-0.0.5.dist-info/licenses/LICENSE
evalyn_sdk_harishatmecs-0.0.5.dist-info/METADATA
evalyn_sdk_harishatmecs-0.0.5.dist-info/WHEEL
evalyn_sdk_harishatmecs-0.0.5.dist-info/top_level.txt
evalyn_sdk_harishatmecs-0.0.5.dist-info/RECORD
