Metadata-Version: 2.4
Name: evalyn_sdk_harishatmecs
Version: 0.0.5
Summary: Python SDK to send evaluation data to an API with support for batch processing
Author-email: Harish Nankani <harish.nankani@atmecs.com>
License-Expression: MIT
Requires-Python: >=3.7
License-File: LICENSE
Requires-Dist: requests
Requires-Dist: pandas
Requires-Dist: openpyxl
Requires-Dist: python-dotenv
Dynamic: license-file
